{
  "project_info": {
    "project_number": "1050649237317",
    "project_id": "project-pab-494fb",
    "storage_bucket": "project-pab-494fb.appspot.com"
  },
  "client": [
    {
      "client_info": {
        "mobilesdk_app_id": "1:1050649237317:android:cf3840e51e2e3e33a0d02c",
        "android_client_info": {
          "package_name": "com.l0122012.alfathroziq.projectpab2024"
        }
      },
      "oauth_client": [],
      "api_key": [
        {
          "current_key": "AIzaSyAvWWORuW16wUGeMDwc82uj2YaMG67L-pQ"
        }
      ],
      "services": {
        "appinvite_service": {
          "other_platform_oauth_client": []
        }
      }
    }
  ],
  "configuration_version": "1"
}